free_proxy_verifyer/__init__.py
free_proxy_verifyer/free_proxy_verifyer.py
free_proxy_verifyer-1.1.4.dist-info/LICENSE.txt
free_proxy_verifyer-1.1.4.dist-info/METADATA
free_proxy_verifyer-1.1.4.dist-info/WHEEL
free_proxy_verifyer-1.1.4.dist-info/top_level.txt
free_proxy_verifyer-1.1.4.dist-info/RECORD
