Metadata-Version: 2.1
Name: free-proxy-verifyer
Version: 1.1.4
Summary: A simple package to verify http and https working proxies.
Home-page: https://github.com/mominurr/free_proxy_verifyer
Author: Mominur Rahman
Author-email: mominurr518@email.com
Classifier: Programming Language :: Python :: 3
Classifier: License :: OSI Approved :: MIT License
Classifier: Operating System :: OS Independent
License-File: LICENSE.txt
Requires-Dist: requests
